ExaminationRoom/__init__.py
ExaminationRoom/drCheckup.py
ExaminationRoom/drCleanup.py
ExaminationRoom/drClusterizer.py
ExaminationRoom/drLogger.py
Surgery/__init__.py
Surgery/drFirstAid.py
Surgery/drMeta.py
Surgery/drOperator.py
Surgery/drPrep.py
Surgery/drRestraints.py
Surgery/drSim.py
Triage/__init__.py
Triage/drConfigTriage.py
Triage/drConfigWriter.py
Triage/drPdbTriage.py
UtilitiesCloset/__init__.py
UtilitiesCloset/drCustomClasses.py
UtilitiesCloset/drFixer.py
UtilitiesCloset/drMethodsWriter.py
UtilitiesCloset/drSelector.py
UtilitiesCloset/drSplash.py
UtilitiesCloset/drSplicer.py
drMD-0.0.2.dist-info/LICENSE
drMD-0.0.2.dist-info/METADATA
drMD-0.0.2.dist-info/WHEEL
drMD-0.0.2.dist-info/top_level.txt
drMD-0.0.2.dist-info/RECORD
