Metadata-Version: 2.1
Name: drMD
Version: 0.0.2
Summary: drMD: Molecular Dynamics for Protein Scientists
Home-page: https://github.com/ESPhoenix/drMD
Author: Dr Eugene Shrimpton-Phoenix
Author-email: Dr Eugene Shrimpton-Phoenix <eshrimpt@ed.ac.uk>
License: MIT
Project-URL: Homepage, https://github.com/ESPhoenix/drMD
Classifier: Programming Language :: Python :: 3
Classifier: License :: OSI Approved :: MIT License
Requires-Python: >=3.9
License-File: LICENSE
Requires-Dist: pyyaml
Requires-Dist: argparse
Requires-Dist: pandas
Requires-Dist: mdtraj
Requires-Dist: numpy
Requires-Dist: matplotlib
Requires-Dist: weasyprint
Requires-Dist: scipy
Requires-Dist: tqdm
Requires-Dist: pdbutils
Requires-Dist: scikit-learn
Requires-Dist: propka
Requires-Dist: mdanalysis
